{
  "version": "7",
  "dialect": "mysql",
  "entries": [
    {
      "idx": 0,
      "version": "5",
      "when": 1726389675728,
      "tag": "0000_youthful_manta",
      "breakpoints": true
    },
    {
      "idx": 1,
      "version": "5",
      "when": 1726443815361,
      "tag": "0001_colossal_trish_tilby",
      "breakpoints": true
    },
    {
      "idx": 2,
      "version": "5",
      "when": 1726902815029,
      "tag": "0002_minor_thaddeus_ross",
      "breakpoints": true
    },
    {
      "idx": 3,
      "version": "5",
      "when": 1727012892006,
      "tag": "0003_gigantic_shotgun",
      "breakpoints": true
    },
    {
      "idx": 4,
      "version": "5",
      "when": 1727141824491,
      "tag": "0004_romantic_surge",
      "breakpoints": true
    },
    {
      "idx": 5,
      "version": "5",
      "when": 1727419081588,
      "tag": "0005_aspiring_leech",
      "breakpoints": true
    },
    {
      "idx": 6,
      "version": "5",
      "when": 1728101992828,
      "tag": "0006_closed_namorita",
      "breakpoints": true
    }
  ]
}